scoutify/__init__.py
scoutify/client.py
scoutify-1.0.5.dist-info/LICENSE.md
scoutify-1.0.5.dist-info/METADATA
scoutify-1.0.5.dist-info/WHEEL
scoutify-1.0.5.dist-info/top_level.txt
scoutify-1.0.5.dist-info/RECORD
