Metadata-Version: 2.1
Name: scoutify
Version: 1.0.5
Summary: A simple Python wrapper library for Spotify WEB API
Home-page: https://github.com/samsan-tech/scoutify
Author: @fijar-lazuardy
Author-email: fijarlaz@gmail.com
License: LICENSE.md
Platform: UNKNOWN
Requires-Dist: requests (>=2.20.0)
Requires-Dist: six (>=1.10.0)
Provides-Extra: doc
Requires-Dist: mkdocs (>=1.12mkdocstrings>=0.13.6mkdocs-material>=6.2.3) ; extra == 'doc'
